datasette_turnstile/__init__.py
datasette_turnstile/middleware.py
datasette_turnstile/utils.py
datasette_turnstile/verification.py
datasette_turnstile/views.py
datasette_turnstile/templates/turnstile_challenge.html
datasette_turnstile-0.1a0.dist-info/licenses/LICENSE
datasette_turnstile-0.1a0.dist-info/METADATA
datasette_turnstile-0.1a0.dist-info/WHEEL
datasette_turnstile-0.1a0.dist-info/entry_points.txt
datasette_turnstile-0.1a0.dist-info/top_level.txt
datasette_turnstile-0.1a0.dist-info/RECORD
