Metadata-Version: 2.4
Name: datasette-turnstile
Version: 0.1a0
Summary: Integrate CAPTCHAs powered by Cloudflare Turnstile
Author: Simon Willison
License-Expression: Apache-2.0
Project-URL: Homepage, https://github.com/simonw/datasette-turnstile
Project-URL: Changelog, https://github.com/simonw/datasette-turnstile/releases
Project-URL: Issues, https://github.com/simonw/datasette-turnstile/issues
Project-URL: CI, https://github.com/simonw/datasette-turnstile/actions
Classifier: Framework :: Datasette
Requires-Python: >=3.10
License-File: LICENSE
Requires-Dist: datasette>=1.0a20
Requires-Dist: httpx>=0.28.1
Dynamic: license-file
